fepzary/__init__.py
fepzary/main.py
fepzary-1.4.dist-info/LICENSE
fepzary-1.4.dist-info/METADATA
fepzary-1.4.dist-info/WHEEL
fepzary-1.4.dist-info/top_level.txt
fepzary-1.4.dist-info/RECORD
